quackup/__init__.py
quackup/cli.py
quackup/config.py
quackup/migration_builder.py
quackup/migrator.py
quackup-0.2.1.dist-info/LICENSE
quackup-0.2.1.dist-info/METADATA
quackup-0.2.1.dist-info/WHEEL
quackup-0.2.1.dist-info/entry_points.txt
quackup-0.2.1.dist-info/top_level.txt
quackup-0.2.1.dist-info/RECORD
