Metadata-Version: 2.2
Name: quackup
Version: 0.2.1
Summary: A simple migration tool for DuckDB databases.
Author-email: Jayme Edwards <jayme.edwards@gmail.com>
License: MIT License
Keywords: duckdb,migrations,database,schema
Classifier: Programming Language :: Python :: 3
Classifier: License :: OSI Approved :: MIT License
Classifier: Operating System :: OS Independent
Requires-Python: >=3.7
License-File: LICENSE
Requires-Dist: click
Requires-Dist: configparser
Requires-Dist: dotenv
Requires-Dist: duckdb
Provides-Extra: test
Requires-Dist: pytest; extra == "test"
Requires-Dist: pytest-mock; extra == "test"
Requires-Dist: pytest-cov; extra == "test"
